retrofix/__init__.py
retrofix/aeat111.py
retrofix/aeat115.py
retrofix/aeat182.py
retrofix/aeat303.py
retrofix/aeat340.py
retrofix/aeat347.py
retrofix/aeat349.py
retrofix/c19.py
retrofix/c32.py
retrofix/c34.py
retrofix/c34_01.py
retrofix/c34_11.py
retrofix/c34_1_la_caixa.py
retrofix/c43.py
retrofix/c57.py
retrofix/c58.py
retrofix/exception.py
retrofix/fields.py
retrofix/formatting.py
retrofix/record.py
retrofix/version.py
retrofix/tests/__init__.py
retrofix/tests/c19.txt
retrofix/tests/c32.txt
retrofix/tests/c34.txt
retrofix/tests/c43.txt
retrofix/tests/c57.txt
retrofix/tests/c58.txt
retrofix/tests/test.py
retrofix-0.32.0.dist-info/LICENSE
retrofix-0.32.0.dist-info/METADATA
retrofix-0.32.0.dist-info/WHEEL
retrofix-0.32.0.dist-info/top_level.txt
retrofix-0.32.0.dist-info/RECORD
