Metadata-Version: 2.1
Name: retrofix
Version: 0.32.0
Summary: retrofix
Home-page: http://www.NaN-tic.com/
Download-URL: https://pypi.python.org/pypi/retrofix/0.32.0
Author: NaN·tic
Author-email: info@nan-tic.com
License: GPL-3
Classifier: Development Status :: 5 - Production/Stable
Classifier: Environment :: No Input/Output (Daemon)
Classifier: Intended Audience :: Developers
Classifier: License :: OSI Approved :: GNU General Public License (GPL)
Classifier: Operating System :: OS Independent
Classifier: Programming Language :: Python :: 2.6
Classifier: Programming Language :: Python :: 2.7
Classifier: Programming Language :: Python :: 3.11
Classifier: Topic :: Software Development :: Libraries
License-File: LICENSE
Requires-Dist: python-stdnum (>=1.5)
